google_books_api/__init__.py
google_books_api/exceptions/google_books_api_exception.py
google_books_api/google_books_api.py
google_books_api/google_books_api_params.py
google_books_api/google_books_api_result.py
google_books_api/models.py
google_books_api-0.1.3.dist-info/LICENSE
google_books_api-0.1.3.dist-info/METADATA
google_books_api-0.1.3.dist-info/WHEEL
google_books_api-0.1.3.dist-info/RECORD
