Metadata-Version: 2.3
Name: google-books-api
Version: 0.1.3
Summary: 
Author: UltraViolet33
Author-email: 93035200+UltraViolet33@users.noreply.github.com
Requires-Python: >=3.10,<4.0
Classifier: Programming Language :: Python :: 3
Classifier: Programming Language :: Python :: 3.10
Classifier: Programming Language :: Python :: 3.11
Classifier: Programming Language :: Python :: 3.12
Classifier: Programming Language :: Python :: 3.13
Requires-Dist: easy-http-requests (>=0.5.1,<0.6.0)
